docs/__init__.py
mzlogging/__init__.py
mzlogging/_consts.py
mzlogging/_mysql_connector.py
mzlogging/logger.py
mzlogging-1.5.2.dist-info/LICENSE.txt
mzlogging-1.5.2.dist-info/METADATA
mzlogging-1.5.2.dist-info/WHEEL
mzlogging-1.5.2.dist-info/top_level.txt
mzlogging-1.5.2.dist-info/RECORD
